mlength/__init__.py
mlength/__main__.py
mlength/py.typed
mlength-0.1.0.dist-info/licenses/LICENSE
mlength-0.1.0.dist-info/METADATA
mlength-0.1.0.dist-info/WHEEL
mlength-0.1.0.dist-info/entry_points.txt
mlength-0.1.0.dist-info/top_level.txt
mlength-0.1.0.dist-info/RECORD
