Metadata-Version: 2.4
Name: mlength
Version: 0.1.0
Summary: gets the length of media files and caches the result
Author: purarue
License-Expression: MIT
Project-URL: Homepage, https://github.com/purarue/mlength
Keywords: media,length,duration,cache
Classifier: Programming Language :: Python
Classifier: Programming Language :: Python :: 3
Classifier: Programming Language :: Python :: 3 :: Only
Classifier: Programming Language :: Python :: 3.10
Classifier: Programming Language :: Python :: 3.11
Classifier: Programming Language :: Python :: 3.12
Classifier: Programming Language :: Python :: 3.13
Classifier: Programming Language :: Python :: 3.14
Requires-Python: >=3.10
License-File: LICENSE
Requires-Dist: click>=8.1.6
Requires-Dist: pymediainfo
Provides-Extra: testing
Requires-Dist: flake8; extra == "testing"
Requires-Dist: mypy; extra == "testing"
Dynamic: license-file
